psutil_home_assistant/__init__.py
psutil_home_assistant-0.0.1.dist-info/LICENSE
psutil_home_assistant-0.0.1.dist-info/METADATA
psutil_home_assistant-0.0.1.dist-info/WHEEL
psutil_home_assistant-0.0.1.dist-info/top_level.txt
psutil_home_assistant-0.0.1.dist-info/zip-safe
psutil_home_assistant-0.0.1.dist-info/RECORD
